LICENSE
MANIFEST.in
README.md
setup.py
tap_doubleclick_campaign_manager/__init__.py
tap_doubleclick_campaign_manager/discover.py
tap_doubleclick_campaign_manager/report_field_type_lookup.json
tap_doubleclick_campaign_manager/schema.py
tap_doubleclick_campaign_manager/sync_reports.py
tap_doubleclick_campaign_manager.egg-info/PKG-INFO
tap_doubleclick_campaign_manager.egg-info/SOURCES.txt
tap_doubleclick_campaign_manager.egg-info/dependency_links.txt
tap_doubleclick_campaign_manager.egg-info/entry_points.txt
tap_doubleclick_campaign_manager.egg-info/requires.txt
tap_doubleclick_campaign_manager.egg-info/top_level.txt