Metadata-Version: 1.1
Name: tap-doubleclick-campaign-manager
Version: 1.2.0
Summary: Singer.io tap for extracting data from the DoubleClick for Campaign Managers API
Home-page: http://singer.io
Author: Stitch
Author-email: UNKNOWN
License: UNKNOWN
Platform: UNKNOWN
Classifier: Programming Language :: Python :: 3 :: Only
